map/__init__.py
map/util_map.py
krit-0.1.0.dist-info/METADATA
krit-0.1.0.dist-info/WHEEL
krit-0.1.0.dist-info/top_level.txt
krit-0.1.0.dist-info/RECORD
